MANIFEST.in
README.txt
bootstrap.py
distribute_setup.py
setup.cfg
setup.py
doc/AUTHORS.txt
doc/BUGS.txt
doc/COPYING.txt
doc/ChangeLog.txt
doc/FAQ.txt
doc/HACKING.txt
doc/INSTALL.txt
doc/LICENCE.txt
doc/NEWS.txt
doc/README.txt
doc/THANKS.txt
doc/TODO.txt
doc/USAGE.txt
doc/bootstrap.cfg.txt
doc/bootstrap.py.txt
doc/glossary.txt
doc/mkbootstrap.txt
doc/related_projects.txt
doc/images/coded_with_wingware.xcf
doc/images/gplv3.xcf
doc/images/osi.xcf
doc/images/python_powered.png
doc/images/originals/coded-with-logo-129x66.png
doc/images/originals/gpl-v3-logo.svg
doc/images/originals/osi_reversing_logotype_color_to_white.png
doc/images/originals/python-powered-w.svg
doc/source/Makefile
doc/source/appendix_a.rst
doc/source/appendix_b.rst
doc/source/bugs.rst
doc/source/conf.py
doc/source/contents.rst
doc/source/faq.rst
doc/source/glossary.rst
doc/source/index.rst
doc/source/install.rst
doc/source/licence.rst
doc/source/make.bat
doc/source/news.rst
doc/source/related_projects.rst
doc/source/_static/coded_with_wingware.png
doc/source/_static/gplv3.png
doc/source/_static/osi.png
doc/source/_static/python_powered.png
doc/source/_static/style.css
doc/source/_templates/layout.html
doc/source/api/everyapp.bootstrap.customize.rst
doc/source/api/everyapp.bootstrap.mkbootstrap.rst
doc/source/api/everyapp.bootstrap.rst
doc/source/api/everyapp.rst
doc/source/api/index.rst
doc/source/credits/authors.rst
doc/source/credits/index.rst
doc/source/credits/thanks.rst
doc/source/development/hacking.rst
doc/source/development/index.rst
doc/source/development/todo.rst
doc/source/man/_common_parts.txt
doc/source/man/bootstrap.cfg.rst
doc/source/man/bootstrap.py.rst
doc/source/man/mkbootstrap.rst
doc/source/usage/bootstrap.cfg.rst
doc/source/usage/bootstrap.py.rst
doc/source/usage/index.rst
doc/source/usage/mkbootstrap.rst
doc/source/usage/usage.rst
etc/bootstrap.cfg
etc/wing-4.wpr
etc/wing.wpr
everyapp/__init__.py
everyapp.bootstrap.egg-info/PKG-INFO
everyapp.bootstrap.egg-info/SOURCES.txt
everyapp.bootstrap.egg-info/dependency_links.txt
everyapp.bootstrap.egg-info/entry_points.txt
everyapp.bootstrap.egg-info/namespace_packages.txt
everyapp.bootstrap.egg-info/not-zip-safe
everyapp.bootstrap.egg-info/requires.txt
everyapp.bootstrap.egg-info/top_level.txt
everyapp/bootstrap/__init__.py
everyapp/bootstrap/bootstrap.cfg
