Metadata-Version: 1.1
Name: everyapp.bootstrap
Version: 0.2.2
Summary: Enhanced virtualenv bootstrap script creation.
Home-page: http://pypi.python.org/pypi/everyapp.bootstrap
Author: Krys Lawrence
Author-email: everyapp@krys.ca
License: GPLv3+
Download-URL: http://pypi.python.org/pypi/everyapp.bootstrap#downloads
Keywords: virtualenv bootstrap everyapp
Platform: UNKNOWN
Classifier: Development Status :: 3 - Alpha
Classifier: Environment :: Console
Classifier: Intended Audience :: Developers
Classifier: License :: OSI Approved :: GNU General Public License (GPL)
Classifier: Natural Language :: English
Classifier: Operating System :: OS Independent
Classifier: Programming Language :: Python :: 2
Classifier: Programming Language :: Python :: 2.4
Classifier: Programming Language :: Python :: 2.5
Classifier: Programming Language :: Python :: 2.6
Classifier: Programming Language :: Python :: 2.7
Classifier: Topic :: Software Development :: Build Tools
Classifier: Topic :: Software Development :: Code Generators
Requires: distribute (>=0.6.24,<0.6.99)
Requires: virtualenv (>=1.7.1,<1.7.99)
Requires: pip (>=1.1,<1.1.99)
Provides: everyapp.bootstrap
